odoo/addons/sale_custom_rounding/README.rst
odoo/addons/sale_custom_rounding/__init__.py
odoo/addons/sale_custom_rounding/__manifest__.py
odoo/addons/sale_custom_rounding/i18n/sale_custom_rounding.pot
odoo/addons/sale_custom_rounding/models/__init__.py
odoo/addons/sale_custom_rounding/models/sale_order.py
odoo/addons/sale_custom_rounding/readme/CONFIGURE.rst
odoo/addons/sale_custom_rounding/readme/CONTRIBUTORS.rst
odoo/addons/sale_custom_rounding/readme/DESCRIPTION.rst
odoo/addons/sale_custom_rounding/readme/USAGE.rst
odoo/addons/sale_custom_rounding/static/description/icon.png
odoo/addons/sale_custom_rounding/static/description/index.html
odoo/addons/sale_custom_rounding/tests/__init__.py
odoo/addons/sale_custom_rounding/tests/test_sale_custom_rounding.py
odoo/addons/sale_custom_rounding/views/sale_views.xml
odoo_addon_sale_custom_rounding-15.0.1.0.1.dist-info/METADATA
odoo_addon_sale_custom_rounding-15.0.1.0.1.dist-info/WHEEL
odoo_addon_sale_custom_rounding-15.0.1.0.1.dist-info/top_level.txt
odoo_addon_sale_custom_rounding-15.0.1.0.1.dist-info/RECORD
